pyreemote/__init__.py
pyreemote/telemeasure.py
pyreemote-11.1.0.dist-info/DESCRIPTION.rst
pyreemote-11.1.0.dist-info/METADATA
pyreemote-11.1.0.dist-info/RECORD
pyreemote-11.1.0.dist-info/WHEEL
pyreemote-11.1.0.dist-info/metadata.json
pyreemote-11.1.0.dist-info/top_level.txt
