Metadata-Version: 2.0
Name: pyreemote
Version: 11.1.0
Summary: Python wrapper for iec870ree
Home-page: https://github.com/gisce/reemote
Author: GISCE-TI, S.L.
Author-email: devel@gisce.net
License: GNU Affero General Public License v3
Platform: UNKNOWN
Requires-Dist: requests
Requires-Dist: iec870ree-moxa
